notebookManagerPackage/__init__.py
notebookManagerPackage/notebook_manager.py
notebookManagerPackage-0.1.dist-info/METADATA
notebookManagerPackage-0.1.dist-info/WHEEL
notebookManagerPackage-0.1.dist-info/top_level.txt
notebookManagerPackage-0.1.dist-info/RECORD
